MANIFEST.in
setup.py
humilis_decrypt/__init__.py
humilis_decrypt/meta.yaml.j2
humilis_decrypt/outputs.yaml.j2
humilis_decrypt/plugin.py
humilis_decrypt/resources.yaml.j2
humilis_decrypt.egg-info/PKG-INFO
humilis_decrypt.egg-info/SOURCES.txt
humilis_decrypt.egg-info/dependency_links.txt
humilis_decrypt.egg-info/entry_points.txt
humilis_decrypt.egg-info/not-zip-safe
humilis_decrypt.egg-info/requires.txt
humilis_decrypt.egg-info/top_level.txt
humilis_decrypt/lambda_function/__init__.py
humilis_decrypt/lambda_function/setup.py
humilis_decrypt/lambda_function/handler/__init__.py