Metadata-Version: 1.1
Name: humilis-decrypt
Version: 0.0.2
Summary: Humilis plug-in to deploy a Lambda humilis_decrypt
Home-page: https://github.com/humilis/humilis-decrypt
Author: German Gomez-Herrero, FindHotel BV
Author-email: german@findhotel.net
License: MIT
Platform: UNKNOWN
Classifier: Programming Language :: Python :: 3
